onacol/__init__.py
onacol/base.py
onacol/config_file.py
onacol/config_schema.py
onacol/flat_schema.py
onacol/onacol.py
onacol-0.3.4.dist-info/METADATA
onacol-0.3.4.dist-info/WHEEL
onacol-0.3.4.dist-info/licenses/LICENSE
onacol-0.3.4.dist-info/RECORD
