Metadata-Version: 2.4
Name: onacol
Version: 0.3.4
Summary: Oh No! Another Configuration Library
License: MIT
License-File: LICENSE
Author: Josef Nevrly
Requires-Python: >=3.9
Classifier: License :: OSI Approved :: MIT License
Classifier: Programming Language :: Python :: 3
Classifier: Programming Language :: Python :: 3.9
Classifier: Programming Language :: Python :: 3.10
Classifier: Programming Language :: Python :: 3.11
Classifier: Programming Language :: Python :: 3.12
Classifier: Programming Language :: Python :: 3.13
Classifier: Programming Language :: Python :: 3.14
Requires-Dist: Cerberus (>=1.3.4,<2.0.0)
Requires-Dist: cascadict (>=0.8.5,<0.9.0)
Requires-Dist: ruamel.yaml (>=0.17.10,<0.18.0)
Project-URL: documentation, https://onacol.readthedocs.io/
Project-URL: homepage, https://github.com/calcite/onacol
